{
  "_embedded": {
    "wordDTOList": [
      {
        "name": "Afghanistan",
        "_embedded": {
          "metadata": { "id": "24" },
          "category": {
            "name": "Country",
            "_embedded": { "metadata": { "id": "1" } }
          }
        }
      },
      {
        "name": "Albania",
        "_embedded": {
          "metadata": { "id": "25" },
          "category": {
            "name": "Country",
            "_embedded": { "metadata": { "id": "1" } }
          }
        }
      },
      {
        "name": "Algeria",
        "_embedded": {
          "metadata": { "id": "26" },
          "category": {
            "name": "Country",
            "_embedded": { "metadata": { "id": "1" } }
          }
        }
      },
      {
        "name": "Andorra",
        "_embedded": {
          "metadata": { "id": "27" },
          "category": {
            "name": "Country",
            "_embedded": { "metadata": { "id": "1" } }
          }
        }
      },
      {
        "name": "Angola",
        "_embedded": {
          "metadata": { "id": "28" },
          "category": {
            "name": "Country",
            "_embedded": { "metadata": { "id": "1" } }
          }
        }
      },
      {
        "name": "Antigua and Barbuda",
        "_embedded": {
          "metadata": { "id": "29" },
          "category": {
            "name": "Country",
            "_embedded": { "metadata": { "id": "1" } }
          }
        }
      },
      {
        "name": "Argentina",
        "_embedded": {
          "metadata": { "id": "30" },
          "category": {
            "name": "Country",
            "_embedded": { "metadata": { "id": "1" } }
          }
        }
      },
      {
        "name": "Armenia",
        "_embedded": {
          "metadata": { "id": "31" },
          "category": {
            "name": "Country",
            "_embedded": { "metadata": { "id": "1" } }
          }
        }
      },
      {
        "name": "Australia",
        "_embedded": {
          "metadata": { "id": "32" },
          "category": {
            "name": "Country",
            "_embedded": { "metadata": { "id": "1" } }
          }
        }
      },
      {
        "name": "Austria",
        "_embedded": {
          "metadata": { "id": "33" },
          "category": {
            "name": "Country",
            "_embedded": { "metadata": { "id": "1" } }
          }
        }
      },
      {
        "name": "Azerbaijan",
        "_embedded": {
          "metadata": { "id": "34" },
          "category": {
            "name": "Country",
            "_embedded": { "metadata": { "id": "1" } }
          }
        }
      },
      {
        "name": "The Bahamas",
        "_embedded": {
          "metadata": { "id": "35" },
          "category": {
            "name": "Country",
            "_embedded": { "metadata": { "id": "1" } }
          }
        }
      },
      {
        "name": "Bahrain",
        "_embedded": {
          "metadata": { "id": "36" },
          "category": {
            "name": "Country",
            "_embedded": { "metadata": { "id": "1" } }
          }
        }
      },
      {
        "name": "Bangladesh",
        "_embedded": {
          "metadata": { "id": "37" },
          "category": {
            "name": "Country",
            "_embedded": { "metadata": { "id": "1" } }
          }
        }
      },
      {
        "name": "Barbados",
        "_embedded": {
          "metadata": { "id": "38" },
          "category": {
            "name": "Country",
            "_embedded": { "metadata": { "id": "1" } }
          }
        }
      },
      {
        "name": "Belarus",
        "_embedded": {
          "metadata": { "id": "39" },
          "category": {
            "name": "Country",
            "_embedded": { "metadata": { "id": "1" } }
          }
        }
      },
      {
        "name": "Belgium",
        "_embedded": {
          "metadata": { "id": "40" },
          "category": {
            "name": "Country",
            "_embedded": { "metadata": { "id": "1" } }
          }
        }
      },
      {
        "name": "Belize",
        "_embedded": {
          "metadata": { "id": "41" },
          "category": {
            "name": "Country",
            "_embedded": { "metadata": { "id": "1" } }
          }
        }
      },
      {
        "name": "Benin",
        "_embedded": {
          "metadata": { "id": "42" },
          "category": {
            "name": "Country",
            "_embedded": { "metadata": { "id": "1" } }
          }
        }
      },
      {
        "name": "Bhutan",
        "_embedded": {
          "metadata": { "id": "43" },
          "category": {
            "name": "Country",
            "_embedded": { "metadata": { "id": "1" } }
          }
        }
      },
      {
        "name": "Bolivia",
        "_embedded": {
          "metadata": { "id": "44" },
          "category": {
            "name": "Country",
            "_embedded": { "metadata": { "id": "1" } }
          }
        }
      },
      {
        "name": "Bosnia and Herzegovina",
        "_embedded": {
          "metadata": { "id": "45" },
          "category": {
            "name": "Country",
            "_embedded": { "metadata": { "id": "1" } }
          }
        }
      },
      {
        "name": "Botswana",
        "_embedded": {
          "metadata": { "id": "46" },
          "category": {
            "name": "Country",
            "_embedded": { "metadata": { "id": "1" } }
          }
        }
      },
      {
        "name": "Brazil",
        "_embedded": {
          "metadata": { "id": "47" },
          "category": {
            "name": "Country",
            "_embedded": { "metadata": { "id": "1" } }
          }
        }
      },
      {
        "name": "Brunei",
        "_embedded": {
          "metadata": { "id": "48" },
          "category": {
            "name": "Country",
            "_embedded": { "metadata": { "id": "1" } }
          }
        }
      },
      {
        "name": "Bulgaria",
        "_embedded": {
          "metadata": { "id": "49" },
          "category": {
            "name": "Country",
            "_embedded": { "metadata": { "id": "1" } }
          }
        }
      },
      {
        "name": "Burkina Faso",
        "_embedded": {
          "metadata": { "id": "50" },
          "category": {
            "name": "Country",
            "_embedded": { "metadata": { "id": "1" } }
          }
        }
      },
      {
        "name": "Burundi",
        "_embedded": {
          "metadata": { "id": "51" },
          "category": {
            "name": "Country",
            "_embedded": { "metadata": { "id": "1" } }
          }
        }
      },
      {
        "name": "Cabo Verde",
        "_embedded": {
          "metadata": { "id": "52" },
          "category": {
            "name": "Country",
            "_embedded": { "metadata": { "id": "1" } }
          }
        }
      },
      {
        "name": "Cambodia",
        "_embedded": {
          "metadata": { "id": "53" },
          "category": {
            "name": "Country",
            "_embedded": { "metadata": { "id": "1" } }
          }
        }
      },
      {
        "name": "Cameroon",
        "_embedded": {
          "metadata": { "id": "54" },
          "category": {
            "name": "Country",
            "_embedded": { "metadata": { "id": "1" } }
          }
        }
      },
      {
        "name": "Canada",
        "_embedded": {
          "metadata": { "id": "55" },
          "category": {
            "name": "Country",
            "_embedded": { "metadata": { "id": "1" } }
          }
        }
      },
      {
        "name": "Central African Republic",
        "_embedded": {
          "metadata": { "id": "56" },
          "category": {
            "name": "Country",
            "_embedded": { "metadata": { "id": "1" } }
          }
        }
      },
      {
        "name": "Chad",
        "_embedded": {
          "metadata": { "id": "57" },
          "category": {
            "name": "Country",
            "_embedded": { "metadata": { "id": "1" } }
          }
        }
      },
      {
        "name": "Chile",
        "_embedded": {
          "metadata": { "id": "58" },
          "category": {
            "name": "Country",
            "_embedded": { "metadata": { "id": "1" } }
          }
        }
      },
      {
        "name": "China",
        "_embedded": {
          "metadata": { "id": "59" },
          "category": {
            "name": "Country",
            "_embedded": { "metadata": { "id": "1" } }
          }
        }
      },
      {
        "name": "Colombia",
        "_embedded": {
          "metadata": { "id": "60" },
          "category": {
            "name": "Country",
            "_embedded": { "metadata": { "id": "1" } }
          }
        }
      },
      {
        "name": "Comoros",
        "_embedded": {
          "metadata": { "id": "61" },
          "category": {
            "name": "Country",
            "_embedded": { "metadata": { "id": "1" } }
          }
        }
      },
      {
        "name": "Congo",
        "_embedded": {
          "metadata": { "id": "62" },
          "category": {
            "name": "Country",
            "_embedded": { "metadata": { "id": "1" } }
          }
        }
      },
      {
        "name": "Costa Rica",
        "_embedded": {
          "metadata": { "id": "63" },
          "category": {
            "name": "Country",
            "_embedded": { "metadata": { "id": "1" } }
          }
        }
      },
      {
        "name": "Croatia",
        "_embedded": {
          "metadata": { "id": "64" },
          "category": {
            "name": "Country",
            "_embedded": { "metadata": { "id": "1" } }
          }
        }
      },
      {
        "name": "Cuba",
        "_embedded": {
          "metadata": { "id": "65" },
          "category": {
            "name": "Country",
            "_embedded": { "metadata": { "id": "1" } }
          }
        }
      },
      {
        "name": "Cyprus",
        "_embedded": {
          "metadata": { "id": "66" },
          "category": {
            "name": "Country",
            "_embedded": { "metadata": { "id": "1" } }
          }
        }
      },
      {
        "name": "Czech Republic",
        "_embedded": {
          "metadata": { "id": "67" },
          "category": {
            "name": "Country",
            "_embedded": { "metadata": { "id": "1" } }
          }
        }
      },
      {
        "name": "Denmark",
        "_embedded": {
          "metadata": { "id": "68" },
          "category": {
            "name": "Country",
            "_embedded": { "metadata": { "id": "1" } }
          }
        }
      },
      {
        "name": "Djibouti",
        "_embedded": {
          "metadata": { "id": "69" },
          "category": {
            "name": "Country",
            "_embedded": { "metadata": { "id": "1" } }
          }
        }
      },
      {
        "name": "Dominica",
        "_embedded": {
          "metadata": { "id": "70" },
          "category": {
            "name": "Country",
            "_embedded": { "metadata": { "id": "1" } }
          }
        }
      },
      {
        "name": "Dominican Republic",
        "_embedded": {
          "metadata": { "id": "71" },
          "category": {
            "name": "Country",
            "_embedded": { "metadata": { "id": "1" } }
          }
        }
      },
      {
        "name": "East Timor",
        "_embedded": {
          "metadata": { "id": "72" },
          "category": {
            "name": "Country",
            "_embedded": { "metadata": { "id": "1" } }
          }
        }
      },
      {
        "name": "Ecuador",
        "_embedded": {
          "metadata": { "id": "73" },
          "category": {
            "name": "Country",
            "_embedded": { "metadata": { "id": "1" } }
          }
        }
      },
      {
        "name": "Egypt",
        "_embedded": {
          "metadata": { "id": "74" },
          "category": {
            "name": "Country",
            "_embedded": { "metadata": { "id": "1" } }
          }
        }
      },
      {
        "name": "El Salvador",
        "_embedded": {
          "metadata": { "id": "75" },
          "category": {
            "name": "Country",
            "_embedded": { "metadata": { "id": "1" } }
          }
        }
      },
      {
        "name": "Equatorial Guinea",
        "_embedded": {
          "metadata": { "id": "76" },
          "category": {
            "name": "Country",
            "_embedded": { "metadata": { "id": "1" } }
          }
        }
      },
      {
        "name": "Eritrea",
        "_embedded": {
          "metadata": { "id": "77" },
          "category": {
            "name": "Country",
            "_embedded": { "metadata": { "id": "1" } }
          }
        }
      },
      {
        "name": "Estonia",
        "_embedded": {
          "metadata": { "id": "78" },
          "category": {
            "name": "Country",
            "_embedded": { "metadata": { "id": "1" } }
          }
        }
      },
      {
        "name": "Eswatini",
        "_embedded": {
          "metadata": { "id": "79" },
          "category": {
            "name": "Country",
            "_embedded": { "metadata": { "id": "1" } }
          }
        }
      },
      {
        "name": "Ethiopia",
        "_embedded": {
          "metadata": { "id": "80" },
          "category": {
            "name": "Country",
            "_embedded": { "metadata": { "id": "1" } }
          }
        }
      },
      {
        "name": "Fiji",
        "_embedded": {
          "metadata": { "id": "81" },
          "category": {
            "name": "Country",
            "_embedded": { "metadata": { "id": "1" } }
          }
        }
      },
      {
        "name": "Finland",
        "_embedded": {
          "metadata": { "id": "82" },
          "category": {
            "name": "Country",
            "_embedded": { "metadata": { "id": "1" } }
          }
        }
      },
      {
        "name": "France",
        "_embedded": {
          "metadata": { "id": "83" },
          "category": {
            "name": "Country",
            "_embedded": { "metadata": { "id": "1" } }
          }
        }
      },
      {
        "name": "Gabon",
        "_embedded": {
          "metadata": { "id": "84" },
          "category": {
            "name": "Country",
            "_embedded": { "metadata": { "id": "1" } }
          }
        }
      },
      {
        "name": "The Gambia",
        "_embedded": {
          "metadata": { "id": "85" },
          "category": {
            "name": "Country",
            "_embedded": { "metadata": { "id": "1" } }
          }
        }
      },
      {
        "name": "Georgia",
        "_embedded": {
          "metadata": { "id": "86" },
          "category": {
            "name": "Country",
            "_embedded": { "metadata": { "id": "1" } }
          }
        }
      },
      {
        "name": "Germany",
        "_embedded": {
          "metadata": { "id": "87" },
          "category": {
            "name": "Country",
            "_embedded": { "metadata": { "id": "1" } }
          }
        }
      },
      {
        "name": "Ghana",
        "_embedded": {
          "metadata": { "id": "88" },
          "category": {
            "name": "Country",
            "_embedded": { "metadata": { "id": "1" } }
          }
        }
      },
      {
        "name": "Greece",
        "_embedded": {
          "metadata": { "id": "89" },
          "category": {
            "name": "Country",
            "_embedded": { "metadata": { "id": "1" } }
          }
        }
      },
      {
        "name": "Grenada",
        "_embedded": {
          "metadata": { "id": "90" },
          "category": {
            "name": "Country",
            "_embedded": { "metadata": { "id": "1" } }
          }
        }
      },
      {
        "name": "Guatemala",
        "_embedded": {
          "metadata": { "id": "91" },
          "category": {
            "name": "Country",
            "_embedded": { "metadata": { "id": "1" } }
          }
        }
      },
      {
        "name": "Guinea",
        "_embedded": {
          "metadata": { "id": "92" },
          "category": {
            "name": "Country",
            "_embedded": { "metadata": { "id": "1" } }
          }
        }
      },
      {
        "name": "Haiti",
        "_embedded": {
          "metadata": { "id": "93" },
          "category": {
            "name": "Country",
            "_embedded": { "metadata": { "id": "1" } }
          }
        }
      },
      {
        "name": "Honduras",
        "_embedded": {
          "metadata": { "id": "94" },
          "category": {
            "name": "Country",
            "_embedded": { "metadata": { "id": "1" } }
          }
        }
      },
      {
        "name": "Hungary",
        "_embedded": {
          "metadata": { "id": "95" },
          "category": {
            "name": "Country",
            "_embedded": { "metadata": { "id": "1" } }
          }
        }
      },
      {
        "name": "Iceland",
        "_embedded": {
          "metadata": { "id": "96" },
          "category": {
            "name": "Country",
            "_embedded": { "metadata": { "id": "1" } }
          }
        }
      },
      {
        "name": "India",
        "_embedded": {
          "metadata": { "id": "97" },
          "category": {
            "name": "Country",
            "_embedded": { "metadata": { "id": "1" } }
          }
        }
      },
      {
        "name": "Indonesia",
        "_embedded": {
          "metadata": { "id": "98" },
          "category": {
            "name": "Country",
            "_embedded": { "metadata": { "id": "1" } }
          }
        }
      },
      {
        "name": "Iran",
        "_embedded": {
          "metadata": { "id": "99" },
          "category": {
            "name": "Country",
            "_embedded": { "metadata": { "id": "1" } }
          }
        }
      },
      {
        "name": "Iraq",
        "_embedded": {
          "metadata": { "id": "100" },
          "category": {
            "name": "Country",
            "_embedded": { "metadata": { "id": "1" } }
          }
        }
      },
      {
        "name": "Ireland",
        "_embedded": {
          "metadata": { "id": "101" },
          "category": {
            "name": "Country",
            "_embedded": { "metadata": { "id": "1" } }
          }
        }
      },
      {
        "name": "Israel",
        "_embedded": {
          "metadata": { "id": "102" },
          "category": {
            "name": "Country",
            "_embedded": { "metadata": { "id": "1" } }
          }
        }
      },
      {
        "name": "Italy",
        "_embedded": {
          "metadata": { "id": "103" },
          "category": {
            "name": "Country",
            "_embedded": { "metadata": { "id": "1" } }
          }
        }
      },
      {
        "name": "Jamaica",
        "_embedded": {
          "metadata": { "id": "104" },
          "category": {
            "name": "Country",
            "_embedded": { "metadata": { "id": "1" } }
          }
        }
      },
      {
        "name": "Japan",
        "_embedded": {
          "metadata": { "id": "105" },
          "category": {
            "name": "Country",
            "_embedded": { "metadata": { "id": "1" } }
          }
        }
      },
      {
        "name": "Jordan",
        "_embedded": {
          "metadata": { "id": "106" },
          "category": {
            "name": "Country",
            "_embedded": { "metadata": { "id": "1" } }
          }
        }
      },
      {
        "name": "Kazakhstan",
        "_embedded": {
          "metadata": { "id": "107" },
          "category": {
            "name": "Country",
            "_embedded": { "metadata": { "id": "1" } }
          }
        }
      },
      {
        "name": "Kenya",
        "_embedded": {
          "metadata": { "id": "108" },
          "category": {
            "name": "Country",
            "_embedded": { "metadata": { "id": "1" } }
          }
        }
      },
      {
        "name": "Kiribati",
        "_embedded": {
          "metadata": { "id": "109" },
          "category": {
            "name": "Country",
            "_embedded": { "metadata": { "id": "1" } }
          }
        }
      },
      {
        "name": "North Korea",
        "_embedded": {
          "metadata": { "id": "110" },
          "category": {
            "name": "Country",
            "_embedded": { "metadata": { "id": "1" } }
          }
        }
      },
      {
        "name": "South Korea",
        "_embedded": {
          "metadata": { "id": "111" },
          "category": {
            "name": "Country",
            "_embedded": { "metadata": { "id": "1" } }
          }
        }
      },
      {
        "name": "Kosovo",
        "_embedded": {
          "metadata": { "id": "112" },
          "category": {
            "name": "Country",
            "_embedded": { "metadata": { "id": "1" } }
          }
        }
      },
      {
        "name": "Kuwait",
        "_embedded": {
          "metadata": { "id": "113" },
          "category": {
            "name": "Country",
            "_embedded": { "metadata": { "id": "1" } }
          }
        }
      },
      {
        "name": "Kyrgyzstan",
        "_embedded": {
          "metadata": { "id": "114" },
          "category": {
            "name": "Country",
            "_embedded": { "metadata": { "id": "1" } }
          }
        }
      },
      {
        "name": "Laos",
        "_embedded": {
          "metadata": { "id": "115" },
          "category": {
            "name": "Country",
            "_embedded": { "metadata": { "id": "1" } }
          }
        }
      },
      {
        "name": "Latvia",
        "_embedded": {
          "metadata": { "id": "116" },
          "category": {
            "name": "Country",
            "_embedded": { "metadata": { "id": "1" } }
          }
        }
      },
      {
        "name": "Lebanon",
        "_embedded": {
          "metadata": { "id": "117" },
          "category": {
            "name": "Country",
            "_embedded": { "metadata": { "id": "1" } }
          }
        }
      },
      {
        "name": "Lesotho",
        "_embedded": {
          "metadata": { "id": "118" },
          "category": {
            "name": "Country",
            "_embedded": { "metadata": { "id": "1" } }
          }
        }
      },
      {
        "name": "Liberia",
        "_embedded": {
          "metadata": { "id": "119" },
          "category": {
            "name": "Country",
            "_embedded": { "metadata": { "id": "1" } }
          }
        }
      },
      {
        "name": "Libya",
        "_embedded": {
          "metadata": { "id": "120" },
          "category": {
            "name": "Country",
            "_embedded": { "metadata": { "id": "1" } }
          }
        }
      },
      {
        "name": "Liechtenstein",
        "_embedded": {
          "metadata": { "id": "121" },
          "category": {
            "name": "Country",
            "_embedded": { "metadata": { "id": "1" } }
          }
        }
      },
      {
        "name": "Lithuania",
        "_embedded": {
          "metadata": { "id": "122" },
          "category": {
            "name": "Country",
            "_embedded": { "metadata": { "id": "1" } }
          }
        }
      },
      {
        "name": "Luxembourg",
        "_embedded": {
          "metadata": { "id": "123" },
          "category": {
            "name": "Country",
            "_embedded": { "metadata": { "id": "1" } }
          }
        }
      },
      {
        "name": "Madagascar",
        "_embedded": {
          "metadata": { "id": "124" },
          "category": {
            "name": "Country",
            "_embedded": { "metadata": { "id": "1" } }
          }
        }
      },
      {
        "name": "Malawi",
        "_embedded": {
          "metadata": { "id": "125" },
          "category": {
            "name": "Country",
            "_embedded": { "metadata": { "id": "1" } }
          }
        }
      },
      {
        "name": "Malaysia",
        "_embedded": {
          "metadata": { "id": "126" },
          "category": {
            "name": "Country",
            "_embedded": { "metadata": { "id": "1" } }
          }
        }
      },
      {
        "name": "Maldives",
        "_embedded": {
          "metadata": { "id": "127" },
          "category": {
            "name": "Country",
            "_embedded": { "metadata": { "id": "1" } }
          }
        }
      },
      {
        "name": "Mali",
        "_embedded": {
          "metadata": { "id": "128" },
          "category": {
            "name": "Country",
            "_embedded": { "metadata": { "id": "1" } }
          }
        }
      },
      {
        "name": "Malta",
        "_embedded": {
          "metadata": { "id": "129" },
          "category": {
            "name": "Country",
            "_embedded": { "metadata": { "id": "1" } }
          }
        }
      },
      {
        "name": "Marshall Islands",
        "_embedded": {
          "metadata": { "id": "130" },
          "category": {
            "name": "Country",
            "_embedded": { "metadata": { "id": "1" } }
          }
        }
      },
      {
        "name": "Mauritania",
        "_embedded": {
          "metadata": { "id": "131" },
          "category": {
            "name": "Country",
            "_embedded": { "metadata": { "id": "1" } }
          }
        }
      },
      {
        "name": "Mauritius",
        "_embedded": {
          "metadata": { "id": "132" },
          "category": {
            "name": "Country",
            "_embedded": { "metadata": { "id": "1" } }
          }
        }
      },
      {
        "name": "Mexico",
        "_embedded": {
          "metadata": { "id": "133" },
          "category": {
            "name": "Country",
            "_embedded": { "metadata": { "id": "1" } }
          }
        }
      },
      {
        "name": "Moldova",
        "_embedded": {
          "metadata": { "id": "134" },
          "category": {
            "name": "Country",
            "_embedded": { "metadata": { "id": "1" } }
          }
        }
      },
      {
        "name": "Monaco",
        "_embedded": {
          "metadata": { "id": "135" },
          "category": {
            "name": "Country",
            "_embedded": { "metadata": { "id": "1" } }
          }
        }
      },
      {
        "name": "Mongolia",
        "_embedded": {
          "metadata": { "id": "136" },
          "category": {
            "name": "Country",
            "_embedded": { "metadata": { "id": "1" } }
          }
        }
      },
      {
        "name": "Montenegro",
        "_embedded": {
          "metadata": { "id": "137" },
          "category": {
            "name": "Country",
            "_embedded": { "metadata": { "id": "1" } }
          }
        }
      },
      {
        "name": "Morocco",
        "_embedded": {
          "metadata": { "id": "138" },
          "category": {
            "name": "Country",
            "_embedded": { "metadata": { "id": "1" } }
          }
        }
      },
      {
        "name": "Mozambique",
        "_embedded": {
          "metadata": { "id": "139" },
          "category": {
            "name": "Country",
            "_embedded": { "metadata": { "id": "1" } }
          }
        }
      },
      {
        "name": "Myanmar",
        "_embedded": {
          "metadata": { "id": "140" },
          "category": {
            "name": "Country",
            "_embedded": { "metadata": { "id": "1" } }
          }
        }
      },
      {
        "name": "Namibia",
        "_embedded": {
          "metadata": { "id": "141" },
          "category": {
            "name": "Country",
            "_embedded": { "metadata": { "id": "1" } }
          }
        }
      },
      {
        "name": "Nauru",
        "_embedded": {
          "metadata": { "id": "142" },
          "category": {
            "name": "Country",
            "_embedded": { "metadata": { "id": "1" } }
          }
        }
      },
      {
        "name": "Nepal",
        "_embedded": {
          "metadata": { "id": "143" },
          "category": {
            "name": "Country",
            "_embedded": { "metadata": { "id": "1" } }
          }
        }
      },
      {
        "name": "Netherlands",
        "_embedded": {
          "metadata": { "id": "144" },
          "category": {
            "name": "Country",
            "_embedded": { "metadata": { "id": "1" } }
          }
        }
      },
      {
        "name": "New Zealand",
        "_embedded": {
          "metadata": { "id": "145" },
          "category": {
            "name": "Country",
            "_embedded": { "metadata": { "id": "1" } }
          }
        }
      },
      {
        "name": "Nicaragua",
        "_embedded": {
          "metadata": { "id": "146" },
          "category": {
            "name": "Country",
            "_embedded": { "metadata": { "id": "1" } }
          }
        }
      },
      {
        "name": "Niger",
        "_embedded": {
          "metadata": { "id": "147" },
          "category": {
            "name": "Country",
            "_embedded": { "metadata": { "id": "1" } }
          }
        }
      },
      {
        "name": "Nigeria",
        "_embedded": {
          "metadata": { "id": "148" },
          "category": {
            "name": "Country",
            "_embedded": { "metadata": { "id": "1" } }
          }
        }
      },
      {
        "name": "North Macedonia",
        "_embedded": {
          "metadata": { "id": "149" },
          "category": {
            "name": "Country",
            "_embedded": { "metadata": { "id": "1" } }
          }
        }
      },
      {
        "name": "Norway",
        "_embedded": {
          "metadata": { "id": "150" },
          "category": {
            "name": "Country",
            "_embedded": { "metadata": { "id": "1" } }
          }
        }
      },
      {
        "name": "Oman",
        "_embedded": {
          "metadata": { "id": "151" },
          "category": {
            "name": "Country",
            "_embedded": { "metadata": { "id": "1" } }
          }
        }
      },
      {
        "name": "Pakistan",
        "_embedded": {
          "metadata": { "id": "152" },
          "category": {
            "name": "Country",
            "_embedded": { "metadata": { "id": "1" } }
          }
        }
      },
      {
        "name": "Palau",
        "_embedded": {
          "metadata": { "id": "153" },
          "category": {
            "name": "Country",
            "_embedded": { "metadata": { "id": "1" } }
          }
        }
      },
      {
        "name": "Panama",
        "_embedded": {
          "metadata": { "id": "154" },
          "category": {
            "name": "Country",
            "_embedded": { "metadata": { "id": "1" } }
          }
        }
      },
      {
        "name": "Papua New Guinea",
        "_embedded": {
          "metadata": { "id": "155" },
          "category": {
            "name": "Country",
            "_embedded": { "metadata": { "id": "1" } }
          }
        }
      },
      {
        "name": "Paraguay",
        "_embedded": {
          "metadata": { "id": "156" },
          "category": {
            "name": "Country",
            "_embedded": { "metadata": { "id": "1" } }
          }
        }
      },
      {
        "name": "Peru",
        "_embedded": {
          "metadata": { "id": "157" },
          "category": {
            "name": "Country",
            "_embedded": { "metadata": { "id": "1" } }
          }
        }
      },
      {
        "name": "Philippines",
        "_embedded": {
          "metadata": { "id": "158" },
          "category": {
            "name": "Country",
            "_embedded": { "metadata": { "id": "1" } }
          }
        }
      },
      {
        "name": "Poland",
        "_embedded": {
          "metadata": { "id": "159" },
          "category": {
            "name": "Country",
            "_embedded": { "metadata": { "id": "1" } }
          }
        }
      },
      {
        "name": "Portugal",
        "_embedded": {
          "metadata": { "id": "160" },
          "category": {
            "name": "Country",
            "_embedded": { "metadata": { "id": "1" } }
          }
        }
      },
      {
        "name": "Qatar",
        "_embedded": {
          "metadata": { "id": "161" },
          "category": {
            "name": "Country",
            "_embedded": { "metadata": { "id": "1" } }
          }
        }
      },
      {
        "name": "Romania",
        "_embedded": {
          "metadata": { "id": "162" },
          "category": {
            "name": "Country",
            "_embedded": { "metadata": { "id": "1" } }
          }
        }
      },
      {
        "name": "Russia",
        "_embedded": {
          "metadata": { "id": "163" },
          "category": {
            "name": "Country",
            "_embedded": { "metadata": { "id": "1" } }
          }
        }
      },
      {
        "name": "Rwanda",
        "_embedded": {
          "metadata": { "id": "164" },
          "category": {
            "name": "Country",
            "_embedded": { "metadata": { "id": "1" } }
          }
        }
      },
      {
        "name": "Saint Kitts and Nevis",
        "_embedded": {
          "metadata": { "id": "165" },
          "category": {
            "name": "Country",
            "_embedded": { "metadata": { "id": "1" } }
          }
        }
      },
      {
        "name": "Saint Lucia",
        "_embedded": {
          "metadata": { "id": "166" },
          "category": {
            "name": "Country",
            "_embedded": { "metadata": { "id": "1" } }
          }
        }
      },
      {
        "name": "Samoa",
        "_embedded": {
          "metadata": { "id": "167" },
          "category": {
            "name": "Country",
            "_embedded": { "metadata": { "id": "1" } }
          }
        }
      },
      {
        "name": "San Marino",
        "_embedded": {
          "metadata": { "id": "168" },
          "category": {
            "name": "Country",
            "_embedded": { "metadata": { "id": "1" } }
          }
        }
      },
      {
        "name": "Saudi Arabia",
        "_embedded": {
          "metadata": { "id": "169" },
          "category": {
            "name": "Country",
            "_embedded": { "metadata": { "id": "1" } }
          }
        }
      },
      {
        "name": "Senegal",
        "_embedded": {
          "metadata": { "id": "170" },
          "category": {
            "name": "Country",
            "_embedded": { "metadata": { "id": "1" } }
          }
        }
      },
      {
        "name": "Serbia",
        "_embedded": {
          "metadata": { "id": "171" },
          "category": {
            "name": "Country",
            "_embedded": { "metadata": { "id": "1" } }
          }
        }
      },
      {
        "name": "Seychelles",
        "_embedded": {
          "metadata": { "id": "172" },
          "category": {
            "name": "Country",
            "_embedded": { "metadata": { "id": "1" } }
          }
        }
      },
      {
        "name": "Sierra Leone",
        "_embedded": {
          "metadata": { "id": "173" },
          "category": {
            "name": "Country",
            "_embedded": { "metadata": { "id": "1" } }
          }
        }
      },
      {
        "name": "Singapore",
        "_embedded": {
          "metadata": { "id": "174" },
          "category": {
            "name": "Country",
            "_embedded": { "metadata": { "id": "1" } }
          }
        }
      },
      {
        "name": "Slovakia",
        "_embedded": {
          "metadata": { "id": "175" },
          "category": {
            "name": "Country",
            "_embedded": { "metadata": { "id": "1" } }
          }
        }
      },
      {
        "name": "Slovenia",
        "_embedded": {
          "metadata": { "id": "176" },
          "category": {
            "name": "Country",
            "_embedded": { "metadata": { "id": "1" } }
          }
        }
      },
      {
        "name": "Solomon Islands",
        "_embedded": {
          "metadata": { "id": "177" },
          "category": {
            "name": "Country",
            "_embedded": { "metadata": { "id": "1" } }
          }
        }
      },
      {
        "name": "Somalia",
        "_embedded": {
          "metadata": { "id": "178" },
          "category": {
            "name": "Country",
            "_embedded": { "metadata": { "id": "1" } }
          }
        }
      },
      {
        "name": "South Africa",
        "_embedded": {
          "metadata": { "id": "179" },
          "category": {
            "name": "Country",
            "_embedded": { "metadata": { "id": "1" } }
          }
        }
      },
      {
        "name": "Spain",
        "_embedded": {
          "metadata": { "id": "180" },
          "category": {
            "name": "Country",
            "_embedded": { "metadata": { "id": "1" } }
          }
        }
      },
      {
        "name": "Sri Lanka",
        "_embedded": {
          "metadata": { "id": "181" },
          "category": {
            "name": "Country",
            "_embedded": { "metadata": { "id": "1" } }
          }
        }
      },
      {
        "name": "Sudan",
        "_embedded": {
          "metadata": { "id": "182" },
          "category": {
            "name": "Country",
            "_embedded": { "metadata": { "id": "1" } }
          }
        }
      },
      {
        "name": "South Sudan",
        "_embedded": {
          "metadata": { "id": "183" },
          "category": {
            "name": "Country",
            "_embedded": { "metadata": { "id": "1" } }
          }
        }
      },
      {
        "name": "Suriname",
        "_embedded": {
          "metadata": { "id": "184" },
          "category": {
            "name": "Country",
            "_embedded": { "metadata": { "id": "1" } }
          }
        }
      },
      {
        "name": "Sweden",
        "_embedded": {
          "metadata": { "id": "185" },
          "category": {
            "name": "Country",
            "_embedded": { "metadata": { "id": "1" } }
          }
        }
      },
      {
        "name": "Switzerland",
        "_embedded": {
          "metadata": { "id": "186" },
          "category": {
            "name": "Country",
            "_embedded": { "metadata": { "id": "1" } }
          }
        }
      },
      {
        "name": "Syria",
        "_embedded": {
          "metadata": { "id": "187" },
          "category": {
            "name": "Country",
            "_embedded": { "metadata": { "id": "1" } }
          }
        }
      },
      {
        "name": "Taiwan",
        "_embedded": {
          "metadata": { "id": "188" },
          "category": {
            "name": "Country",
            "_embedded": { "metadata": { "id": "1" } }
          }
        }
      },
      {
        "name": "Tajikistan",
        "_embedded": {
          "metadata": { "id": "189" },
          "category": {
            "name": "Country",
            "_embedded": { "metadata": { "id": "1" } }
          }
        }
      },
      {
        "name": "Tanzania",
        "_embedded": {
          "metadata": { "id": "190" },
          "category": {
            "name": "Country",
            "_embedded": { "metadata": { "id": "1" } }
          }
        }
      },
      {
        "name": "Thailand",
        "_embedded": {
          "metadata": { "id": "191" },
          "category": {
            "name": "Country",
            "_embedded": { "metadata": { "id": "1" } }
          }
        }
      },
      {
        "name": "Togo",
        "_embedded": {
          "metadata": { "id": "192" },
          "category": {
            "name": "Country",
            "_embedded": { "metadata": { "id": "1" } }
          }
        }
      },
      {
        "name": "Tonga",
        "_embedded": {
          "metadata": { "id": "193" },
          "category": {
            "name": "Country",
            "_embedded": { "metadata": { "id": "1" } }
          }
        }
      },
      {
        "name": "Trinidad and Tobago",
        "_embedded": {
          "metadata": { "id": "194" },
          "category": {
            "name": "Country",
            "_embedded": { "metadata": { "id": "1" } }
          }
        }
      },
      {
        "name": "Tunisia",
        "_embedded": {
          "metadata": { "id": "195" },
          "category": {
            "name": "Country",
            "_embedded": { "metadata": { "id": "1" } }
          }
        }
      },
      {
        "name": "Turkey",
        "_embedded": {
          "metadata": { "id": "196" },
          "category": {
            "name": "Country",
            "_embedded": { "metadata": { "id": "1" } }
          }
        }
      },
      {
        "name": "Turkmenistan",
        "_embedded": {
          "metadata": { "id": "197" },
          "category": {
            "name": "Country",
            "_embedded": { "metadata": { "id": "1" } }
          }
        }
      },
      {
        "name": "Tuvalu",
        "_embedded": {
          "metadata": { "id": "198" },
          "category": {
            "name": "Country",
            "_embedded": { "metadata": { "id": "1" } }
          }
        }
      },
      {
        "name": "Uganda",
        "_embedded": {
          "metadata": { "id": "199" },
          "category": {
            "name": "Country",
            "_embedded": { "metadata": { "id": "1" } }
          }
        }
      },
      {
        "name": "Ukraine",
        "_embedded": {
          "metadata": { "id": "200" },
          "category": {
            "name": "Country",
            "_embedded": { "metadata": { "id": "1" } }
          }
        }
      },
      {
        "name": "United Arab Emirates",
        "_embedded": {
          "metadata": { "id": "201" },
          "category": {
            "name": "Country",
            "_embedded": { "metadata": { "id": "1" } }
          }
        }
      },
      {
        "name": "United Kingdom",
        "_embedded": {
          "metadata": { "id": "202" },
          "category": {
            "name": "Country",
            "_embedded": { "metadata": { "id": "1" } }
          }
        }
      },
      {
        "name": "United States",
        "_embedded": {
          "metadata": { "id": "203" },
          "category": {
            "name": "Country",
            "_embedded": { "metadata": { "id": "1" } }
          }
        }
      },
      {
        "name": "Uruguay",
        "_embedded": {
          "metadata": { "id": "204" },
          "category": {
            "name": "Country",
            "_embedded": { "metadata": { "id": "1" } }
          }
        }
      },
      {
        "name": "Uzbekistan",
        "_embedded": {
          "metadata": { "id": "205" },
          "category": {
            "name": "Country",
            "_embedded": { "metadata": { "id": "1" } }
          }
        }
      },
      {
        "name": "Vanuatu",
        "_embedded": {
          "metadata": { "id": "206" },
          "category": {
            "name": "Country",
            "_embedded": { "metadata": { "id": "1" } }
          }
        }
      },
      {
        "name": "Vatican City",
        "_embedded": {
          "metadata": { "id": "207" },
          "category": {
            "name": "Country",
            "_embedded": { "metadata": { "id": "1" } }
          }
        }
      },
      {
        "name": "Venezuela",
        "_embedded": {
          "metadata": { "id": "208" },
          "category": {
            "name": "Country",
            "_embedded": { "metadata": { "id": "1" } }
          }
        }
      },
      {
        "name": "Vietnam",
        "_embedded": {
          "metadata": { "id": "209" },
          "category": {
            "name": "Country",
            "_embedded": { "metadata": { "id": "1" } }
          }
        }
      },
      {
        "name": "Yemen",
        "_embedded": {
          "metadata": { "id": "210" },
          "category": {
            "name": "Country",
            "_embedded": { "metadata": { "id": "1" } }
          }
        }
      },
      {
        "name": "Zambia",
        "_embedded": {
          "metadata": { "id": "211" },
          "category": {
            "name": "Country",
            "_embedded": { "metadata": { "id": "1" } }
          }
        }
      },
      {
        "name": "Zimbabwe",
        "_embedded": {
          "metadata": { "id": "212" },
          "category": {
            "name": "Country",
            "_embedded": { "metadata": { "id": "1" } }
          }
        }
      },
      {
        "name": "Dog",
        "_embedded": {
          "metadata": { "id": "213" },
          "category": {
            "name": "Animal",
            "_embedded": { "metadata": { "id": "2" } }
          }
        }
      },
      {
        "name": "Puppy",
        "_embedded": {
          "metadata": { "id": "214" },
          "category": {
            "name": "Animal",
            "_embedded": { "metadata": { "id": "2" } }
          }
        }
      },
      {
        "name": "Turtle",
        "_embedded": {
          "metadata": { "id": "215" },
          "category": {
            "name": "Animal",
            "_embedded": { "metadata": { "id": "2" } }
          }
        }
      },
      {
        "name": "Rabbit",
        "_embedded": {
          "metadata": { "id": "216" },
          "category": {
            "name": "Animal",
            "_embedded": { "metadata": { "id": "2" } }
          }
        }
      },
      {
        "name": "Parrot",
        "_embedded": {
          "metadata": { "id": "217" },
          "category": {
            "name": "Animal",
            "_embedded": { "metadata": { "id": "2" } }
          }
        }
      },
      {
        "name": "Cat",
        "_embedded": {
          "metadata": { "id": "218" },
          "category": {
            "name": "Animal",
            "_embedded": { "metadata": { "id": "2" } }
          }
        }
      },
      {
        "name": "Kitten",
        "_embedded": {
          "metadata": { "id": "219" },
          "category": {
            "name": "Animal",
            "_embedded": { "metadata": { "id": "2" } }
          }
        }
      },
      {
        "name": "Goldfish",
        "_embedded": {
          "metadata": { "id": "220" },
          "category": {
            "name": "Animal",
            "_embedded": { "metadata": { "id": "2" } }
          }
        }
      },
      {
        "name": "Mouse",
        "_embedded": {
          "metadata": { "id": "221" },
          "category": {
            "name": "Animal",
            "_embedded": { "metadata": { "id": "2" } }
          }
        }
      },
      {
        "name": "Fish",
        "_embedded": {
          "metadata": { "id": "222" },
          "category": {
            "name": "Animal",
            "_embedded": { "metadata": { "id": "2" } }
          }
        }
      },
      {
        "name": "Hamster",
        "_embedded": {
          "metadata": { "id": "223" },
          "category": {
            "name": "Animal",
            "_embedded": { "metadata": { "id": "2" } }
          }
        }
      },
      {
        "name": "Cow",
        "_embedded": {
          "metadata": { "id": "224" },
          "category": {
            "name": "Animal",
            "_embedded": { "metadata": { "id": "2" } }
          }
        }
      },
      {
        "name": "Rabbit",
        "_embedded": {
          "metadata": { "id": "225" },
          "category": {
            "name": "Animal",
            "_embedded": { "metadata": { "id": "2" } }
          }
        }
      },
      {
        "name": "Ducks",
        "_embedded": {
          "metadata": { "id": "226" },
          "category": {
            "name": "Animal",
            "_embedded": { "metadata": { "id": "2" } }
          }
        }
      },
      {
        "name": "Shrimp",
        "_embedded": {
          "metadata": { "id": "227" },
          "category": {
            "name": "Animal",
            "_embedded": { "metadata": { "id": "2" } }
          }
        }
      },
      {
        "name": "Pig",
        "_embedded": {
          "metadata": { "id": "228" },
          "category": {
            "name": "Animal",
            "_embedded": { "metadata": { "id": "2" } }
          }
        }
      },
      {
        "name": "Goat",
        "_embedded": {
          "metadata": { "id": "229" },
          "category": {
            "name": "Animal",
            "_embedded": { "metadata": { "id": "2" } }
          }
        }
      },
      {
        "name": "Crab",
        "_embedded": {
          "metadata": { "id": "230" },
          "category": {
            "name": "Animal",
            "_embedded": { "metadata": { "id": "2" } }
          }
        }
      },
      {
        "name": "Deer",
        "_embedded": {
          "metadata": { "id": "231" },
          "category": {
            "name": "Animal",
            "_embedded": { "metadata": { "id": "2" } }
          }
        }
      },
      {
        "name": "Bee",
        "_embedded": {
          "metadata": { "id": "232" },
          "category": {
            "name": "Animal",
            "_embedded": { "metadata": { "id": "2" } }
          }
        }
      },
      {
        "name": "Sheep",
        "_embedded": {
          "metadata": { "id": "233" },
          "category": {
            "name": "Animal",
            "_embedded": { "metadata": { "id": "2" } }
          }
        }
      },
      {
        "name": "Fish",
        "_embedded": {
          "metadata": { "id": "234" },
          "category": {
            "name": "Animal",
            "_embedded": { "metadata": { "id": "2" } }
          }
        }
      },
      {
        "name": "Turkey",
        "_embedded": {
          "metadata": { "id": "235" },
          "category": {
            "name": "Animal",
            "_embedded": { "metadata": { "id": "2" } }
          }
        }
      },
      {
        "name": "Dove",
        "_embedded": {
          "metadata": { "id": "236" },
          "category": {
            "name": "Animal",
            "_embedded": { "metadata": { "id": "2" } }
          }
        }
      },
      {
        "name": "Chicken",
        "_embedded": {
          "metadata": { "id": "237" },
          "category": {
            "name": "Animal",
            "_embedded": { "metadata": { "id": "2" } }
          }
        }
      },
      {
        "name": "Horse",
        "_embedded": {
          "metadata": { "id": "238" },
          "category": {
            "name": "Animal",
            "_embedded": { "metadata": { "id": "2" } }
          }
        }
      },
      {
        "name": "Crow",
        "_embedded": {
          "metadata": { "id": "239" },
          "category": {
            "name": "Animal",
            "_embedded": { "metadata": { "id": "2" } }
          }
        }
      },
      {
        "name": "Peacock",
        "_embedded": {
          "metadata": { "id": "240" },
          "category": {
            "name": "Animal",
            "_embedded": { "metadata": { "id": "2" } }
          }
        }
      },
      {
        "name": "Dove",
        "_embedded": {
          "metadata": { "id": "241" },
          "category": {
            "name": "Animal",
            "_embedded": { "metadata": { "id": "2" } }
          }
        }
      },
      {
        "name": "Sparrow",
        "_embedded": {
          "metadata": { "id": "242" },
          "category": {
            "name": "Animal",
            "_embedded": { "metadata": { "id": "2" } }
          }
        }
      },
      {
        "name": "Goose",
        "_embedded": {
          "metadata": { "id": "243" },
          "category": {
            "name": "Animal",
            "_embedded": { "metadata": { "id": "2" } }
          }
        }
      },
      {
        "name": "Stork",
        "_embedded": {
          "metadata": { "id": "244" },
          "category": {
            "name": "Animal",
            "_embedded": { "metadata": { "id": "2" } }
          }
        }
      },
      {
        "name": "Pigeon",
        "_embedded": {
          "metadata": { "id": "245" },
          "category": {
            "name": "Animal",
            "_embedded": { "metadata": { "id": "2" } }
          }
        }
      },
      {
        "name": "Turkey",
        "_embedded": {
          "metadata": { "id": "246" },
          "category": {
            "name": "Animal",
            "_embedded": { "metadata": { "id": "2" } }
          }
        }
      },
      {
        "name": "Hawk",
        "_embedded": {
          "metadata": { "id": "247" },
          "category": {
            "name": "Animal",
            "_embedded": { "metadata": { "id": "2" } }
          }
        }
      },
      {
        "name": "Bald eagle",
        "_embedded": {
          "metadata": { "id": "248" },
          "category": {
            "name": "Animal",
            "_embedded": { "metadata": { "id": "2" } }
          }
        }
      },
      {
        "name": "Raven",
        "_embedded": {
          "metadata": { "id": "249" },
          "category": {
            "name": "Animal",
            "_embedded": { "metadata": { "id": "2" } }
          }
        }
      },
      {
        "name": "Parrot",
        "_embedded": {
          "metadata": { "id": "250" },
          "category": {
            "name": "Animal",
            "_embedded": { "metadata": { "id": "2" } }
          }
        }
      },
      {
        "name": "Flamingo",
        "_embedded": {
          "metadata": { "id": "251" },
          "category": {
            "name": "Animal",
            "_embedded": { "metadata": { "id": "2" } }
          }
        }
      },
      {
        "name": "Seagull",
        "_embedded": {
          "metadata": { "id": "252" },
          "category": {
            "name": "Animal",
            "_embedded": { "metadata": { "id": "2" } }
          }
        }
      },
      {
        "name": "Ostrich",
        "_embedded": {
          "metadata": { "id": "253" },
          "category": {
            "name": "Animal",
            "_embedded": { "metadata": { "id": "2" } }
          }
        }
      },
      {
        "name": "Black bird",
        "_embedded": {
          "metadata": { "id": "254" },
          "category": {
            "name": "Animal",
            "_embedded": { "metadata": { "id": "2" } }
          }
        }
      },
      {
        "name": "Penguin",
        "_embedded": {
          "metadata": { "id": "255" },
          "category": {
            "name": "Animal",
            "_embedded": { "metadata": { "id": "2" } }
          }
        }
      },
      {
        "name": "Robin",
        "_embedded": {
          "metadata": { "id": "256" },
          "category": {
            "name": "Animal",
            "_embedded": { "metadata": { "id": "2" } }
          }
        }
      },
      {
        "name": "Swan",
        "_embedded": {
          "metadata": { "id": "257" },
          "category": {
            "name": "Animal",
            "_embedded": { "metadata": { "id": "2" } }
          }
        }
      },
      {
        "name": "Owl",
        "_embedded": {
          "metadata": { "id": "258" },
          "category": {
            "name": "Animal",
            "_embedded": { "metadata": { "id": "2" } }
          }
        }
      },
      {
        "name": "Woodpecker",
        "_embedded": {
          "metadata": { "id": "259" },
          "category": {
            "name": "Animal",
            "_embedded": { "metadata": { "id": "2" } }
          }
        }
      },
      {
        "name": "Squirrel",
        "_embedded": {
          "metadata": { "id": "260" },
          "category": {
            "name": "Animal",
            "_embedded": { "metadata": { "id": "2" } }
          }
        }
      },
      {
        "name": "Dog",
        "_embedded": {
          "metadata": { "id": "261" },
          "category": {
            "name": "Animal",
            "_embedded": { "metadata": { "id": "2" } }
          }
        }
      },
      {
        "name": "Chimpanzee",
        "_embedded": {
          "metadata": { "id": "262" },
          "category": {
            "name": "Animal",
            "_embedded": { "metadata": { "id": "2" } }
          }
        }
      },
      {
        "name": "Ox",
        "_embedded": {
          "metadata": { "id": "263" },
          "category": {
            "name": "Animal",
            "_embedded": { "metadata": { "id": "2" } }
          }
        }
      },
      {
        "name": "Lion",
        "_embedded": {
          "metadata": { "id": "264" },
          "category": {
            "name": "Animal",
            "_embedded": { "metadata": { "id": "2" } }
          }
        }
      },
      {
        "name": "Panda",
        "_embedded": {
          "metadata": { "id": "265" },
          "category": {
            "name": "Animal",
            "_embedded": { "metadata": { "id": "2" } }
          }
        }
      },
      {
        "name": "Walrus",
        "_embedded": {
          "metadata": { "id": "266" },
          "category": {
            "name": "Animal",
            "_embedded": { "metadata": { "id": "2" } }
          }
        }
      },
      {
        "name": "Otter",
        "_embedded": {
          "metadata": { "id": "267" },
          "category": {
            "name": "Animal",
            "_embedded": { "metadata": { "id": "2" } }
          }
        }
      },
      {
        "name": "Mouse",
        "_embedded": {
          "metadata": { "id": "268" },
          "category": {
            "name": "Animal",
            "_embedded": { "metadata": { "id": "2" } }
          }
        }
      },
      {
        "name": "Kangaroo",
        "_embedded": {
          "metadata": { "id": "269" },
          "category": {
            "name": "Animal",
            "_embedded": { "metadata": { "id": "2" } }
          }
        }
      },
      {
        "name": "Goat",
        "_embedded": {
          "metadata": { "id": "270" },
          "category": {
            "name": "Animal",
            "_embedded": { "metadata": { "id": "2" } }
          }
        }
      },
      {
        "name": "Horse",
        "_embedded": {
          "metadata": { "id": "271" },
          "category": {
            "name": "Animal",
            "_embedded": { "metadata": { "id": "2" } }
          }
        }
      },
      {
        "name": "Monkey",
        "_embedded": {
          "metadata": { "id": "272" },
          "category": {
            "name": "Animal",
            "_embedded": { "metadata": { "id": "2" } }
          }
        }
      },
      {
        "name": "Cow",
        "_embedded": {
          "metadata": { "id": "273" },
          "category": {
            "name": "Animal",
            "_embedded": { "metadata": { "id": "2" } }
          }
        }
      },
      {
        "name": "Koala",
        "_embedded": {
          "metadata": { "id": "274" },
          "category": {
            "name": "Animal",
            "_embedded": { "metadata": { "id": "2" } }
          }
        }
      },
      {
        "name": "Mole",
        "_embedded": {
          "metadata": { "id": "275" },
          "category": {
            "name": "Animal",
            "_embedded": { "metadata": { "id": "2" } }
          }
        }
      },
      {
        "name": "Elephant",
        "_embedded": {
          "metadata": { "id": "276" },
          "category": {
            "name": "Animal",
            "_embedded": { "metadata": { "id": "2" } }
          }
        }
      },
      {
        "name": "Leopard",
        "_embedded": {
          "metadata": { "id": "277" },
          "category": {
            "name": "Animal",
            "_embedded": { "metadata": { "id": "2" } }
          }
        }
      },
      {
        "name": "Hippopotamus",
        "_embedded": {
          "metadata": { "id": "278" },
          "category": {
            "name": "Animal",
            "_embedded": { "metadata": { "id": "2" } }
          }
        }
      },
      {
        "name": "Giraffe",
        "_embedded": {
          "metadata": { "id": "279" },
          "category": {
            "name": "Animal",
            "_embedded": { "metadata": { "id": "2" } }
          }
        }
      },
      {
        "name": "Fox",
        "_embedded": {
          "metadata": { "id": "280" },
          "category": {
            "name": "Animal",
            "_embedded": { "metadata": { "id": "2" } }
          }
        }
      },
      {
        "name": "Coyote",
        "_embedded": {
          "metadata": { "id": "281" },
          "category": {
            "name": "Animal",
            "_embedded": { "metadata": { "id": "2" } }
          }
        }
      },
      {
        "name": "Hedgehong",
        "_embedded": {
          "metadata": { "id": "282" },
          "category": {
            "name": "Animal",
            "_embedded": { "metadata": { "id": "2" } }
          }
        }
      },
      {
        "name": "Sheep",
        "_embedded": {
          "metadata": { "id": "283" },
          "category": {
            "name": "Animal",
            "_embedded": { "metadata": { "id": "2" } }
          }
        }
      },
      {
        "name": "Deer",
        "_embedded": {
          "metadata": { "id": "284" },
          "category": {
            "name": "Animal",
            "_embedded": { "metadata": { "id": "2" } }
          }
        }
      },
      {
        "name": "Giraffe",
        "_embedded": {
          "metadata": { "id": "285" },
          "category": {
            "name": "Animal",
            "_embedded": { "metadata": { "id": "2" } }
          }
        }
      },
      {
        "name": "Woodpecker",
        "_embedded": {
          "metadata": { "id": "286" },
          "category": {
            "name": "Animal",
            "_embedded": { "metadata": { "id": "2" } }
          }
        }
      },
      {
        "name": "Camel",
        "_embedded": {
          "metadata": { "id": "287" },
          "category": {
            "name": "Animal",
            "_embedded": { "metadata": { "id": "2" } }
          }
        }
      },
      {
        "name": "Starfish",
        "_embedded": {
          "metadata": { "id": "288" },
          "category": {
            "name": "Animal",
            "_embedded": { "metadata": { "id": "2" } }
          }
        }
      },
      {
        "name": "Koala",
        "_embedded": {
          "metadata": { "id": "289" },
          "category": {
            "name": "Animal",
            "_embedded": { "metadata": { "id": "2" } }
          }
        }
      },
      {
        "name": "Alligator",
        "_embedded": {
          "metadata": { "id": "290" },
          "category": {
            "name": "Animal",
            "_embedded": { "metadata": { "id": "2" } }
          }
        }
      },
      {
        "name": "Owl",
        "_embedded": {
          "metadata": { "id": "291" },
          "category": {
            "name": "Animal",
            "_embedded": { "metadata": { "id": "2" } }
          }
        }
      },
      {
        "name": "Tiger",
        "_embedded": {
          "metadata": { "id": "292" },
          "category": {
            "name": "Animal",
            "_embedded": { "metadata": { "id": "2" } }
          }
        }
      },
      {
        "name": "Bear",
        "_embedded": {
          "metadata": { "id": "293" },
          "category": {
            "name": "Animal",
            "_embedded": { "metadata": { "id": "2" } }
          }
        }
      },
      {
        "name": "Blue whale",
        "_embedded": {
          "metadata": { "id": "294" },
          "category": {
            "name": "Animal",
            "_embedded": { "metadata": { "id": "2" } }
          }
        }
      },
      {
        "name": "Coyote",
        "_embedded": {
          "metadata": { "id": "295" },
          "category": {
            "name": "Animal",
            "_embedded": { "metadata": { "id": "2" } }
          }
        }
      },
      {
        "name": "Chimpanzee",
        "_embedded": {
          "metadata": { "id": "296" },
          "category": {
            "name": "Animal",
            "_embedded": { "metadata": { "id": "2" } }
          }
        }
      },
      {
        "name": "Raccoon",
        "_embedded": {
          "metadata": { "id": "297" },
          "category": {
            "name": "Animal",
            "_embedded": { "metadata": { "id": "2" } }
          }
        }
      },
      {
        "name": "Lion",
        "_embedded": {
          "metadata": { "id": "298" },
          "category": {
            "name": "Animal",
            "_embedded": { "metadata": { "id": "2" } }
          }
        }
      },
      {
        "name": "Arctic wolf",
        "_embedded": {
          "metadata": { "id": "299" },
          "category": {
            "name": "Animal",
            "_embedded": { "metadata": { "id": "2" } }
          }
        }
      },
      {
        "name": "Crocodile",
        "_embedded": {
          "metadata": { "id": "300" },
          "category": {
            "name": "Animal",
            "_embedded": { "metadata": { "id": "2" } }
          }
        }
      },
      {
        "name": "Dolphin",
        "_embedded": {
          "metadata": { "id": "301" },
          "category": {
            "name": "Animal",
            "_embedded": { "metadata": { "id": "2" } }
          }
        }
      },
      {
        "name": "Elephant",
        "_embedded": {
          "metadata": { "id": "302" },
          "category": {
            "name": "Animal",
            "_embedded": { "metadata": { "id": "2" } }
          }
        }
      },
      {
        "name": "Squirrel",
        "_embedded": {
          "metadata": { "id": "303" },
          "category": {
            "name": "Animal",
            "_embedded": { "metadata": { "id": "2" } }
          }
        }
      },
      {
        "name": "Snake",
        "_embedded": {
          "metadata": { "id": "304" },
          "category": {
            "name": "Animal",
            "_embedded": { "metadata": { "id": "2" } }
          }
        }
      },
      {
        "name": "Kangaroo",
        "_embedded": {
          "metadata": { "id": "305" },
          "category": {
            "name": "Animal",
            "_embedded": { "metadata": { "id": "2" } }
          }
        }
      },
      {
        "name": "Hippopotamus",
        "_embedded": {
          "metadata": { "id": "306" },
          "category": {
            "name": "Animal",
            "_embedded": { "metadata": { "id": "2" } }
          }
        }
      },
      {
        "name": "Elk",
        "_embedded": {
          "metadata": { "id": "307" },
          "category": {
            "name": "Animal",
            "_embedded": { "metadata": { "id": "2" } }
          }
        }
      },
      {
        "name": "Fox",
        "_embedded": {
          "metadata": { "id": "308" },
          "category": {
            "name": "Animal",
            "_embedded": { "metadata": { "id": "2" } }
          }
        }
      },
      {
        "name": "Gorilla",
        "_embedded": {
          "metadata": { "id": "309" },
          "category": {
            "name": "Animal",
            "_embedded": { "metadata": { "id": "2" } }
          }
        }
      },
      {
        "name": "Bat",
        "_embedded": {
          "metadata": { "id": "310" },
          "category": {
            "name": "Animal",
            "_embedded": { "metadata": { "id": "2" } }
          }
        }
      },
      {
        "name": "Hare",
        "_embedded": {
          "metadata": { "id": "311" },
          "category": {
            "name": "Animal",
            "_embedded": { "metadata": { "id": "2" } }
          }
        }
      },
      {
        "name": "Toad",
        "_embedded": {
          "metadata": { "id": "312" },
          "category": {
            "name": "Animal",
            "_embedded": { "metadata": { "id": "2" } }
          }
        }
      },
      {
        "name": "Frog",
        "_embedded": {
          "metadata": { "id": "313" },
          "category": {
            "name": "Animal",
            "_embedded": { "metadata": { "id": "2" } }
          }
        }
      },
      {
        "name": "Deer",
        "_embedded": {
          "metadata": { "id": "314" },
          "category": {
            "name": "Animal",
            "_embedded": { "metadata": { "id": "2" } }
          }
        }
      },
      {
        "name": "Rat",
        "_embedded": {
          "metadata": { "id": "315" },
          "category": {
            "name": "Animal",
            "_embedded": { "metadata": { "id": "2" } }
          }
        }
      },
      {
        "name": "Badger",
        "_embedded": {
          "metadata": { "id": "316" },
          "category": {
            "name": "Animal",
            "_embedded": { "metadata": { "id": "2" } }
          }
        }
      },
      {
        "name": "Lizard",
        "_embedded": {
          "metadata": { "id": "317" },
          "category": {
            "name": "Animal",
            "_embedded": { "metadata": { "id": "2" } }
          }
        }
      },
      {
        "name": "Mole",
        "_embedded": {
          "metadata": { "id": "318" },
          "category": {
            "name": "Animal",
            "_embedded": { "metadata": { "id": "2" } }
          }
        }
      },
      {
        "name": "Hedgehog",
        "_embedded": {
          "metadata": { "id": "319" },
          "category": {
            "name": "Animal",
            "_embedded": { "metadata": { "id": "2" } }
          }
        }
      },
      {
        "name": "Otter",
        "_embedded": {
          "metadata": { "id": "320" },
          "category": {
            "name": "Animal",
            "_embedded": { "metadata": { "id": "2" } }
          }
        }
      },
      {
        "name": "Reindeer",
        "_embedded": {
          "metadata": { "id": "321" },
          "category": {
            "name": "Animal",
            "_embedded": { "metadata": { "id": "2" } }
          }
        }
      },
      {
        "name": "Crab",
        "_embedded": {
          "metadata": { "id": "322" },
          "category": {
            "name": "Animal",
            "_embedded": { "metadata": { "id": "2" } }
          }
        }
      },
      {
        "name": "Fish",
        "_embedded": {
          "metadata": { "id": "323" },
          "category": {
            "name": "Animal",
            "_embedded": { "metadata": { "id": "2" } }
          }
        }
      },
      {
        "name": "Seal",
        "_embedded": {
          "metadata": { "id": "324" },
          "category": {
            "name": "Animal",
            "_embedded": { "metadata": { "id": "2" } }
          }
        }
      },
      {
        "name": "Octopus",
        "_embedded": {
          "metadata": { "id": "325" },
          "category": {
            "name": "Animal",
            "_embedded": { "metadata": { "id": "2" } }
          }
        }
      },
      {
        "name": "Shark",
        "_embedded": {
          "metadata": { "id": "326" },
          "category": {
            "name": "Animal",
            "_embedded": { "metadata": { "id": "2" } }
          }
        }
      },
      {
        "name": "Seahorse",
        "_embedded": {
          "metadata": { "id": "327" },
          "category": {
            "name": "Animal",
            "_embedded": { "metadata": { "id": "2" } }
          }
        }
      },
      {
        "name": "Walrus",
        "_embedded": {
          "metadata": { "id": "328" },
          "category": {
            "name": "Animal",
            "_embedded": { "metadata": { "id": "2" } }
          }
        }
      },
      {
        "name": "Starfish",
        "_embedded": {
          "metadata": { "id": "329" },
          "category": {
            "name": "Animal",
            "_embedded": { "metadata": { "id": "2" } }
          }
        }
      },
      {
        "name": "Whale",
        "_embedded": {
          "metadata": { "id": "330" },
          "category": {
            "name": "Animal",
            "_embedded": { "metadata": { "id": "2" } }
          }
        }
      },
      {
        "name": "Penguin",
        "_embedded": {
          "metadata": { "id": "331" },
          "category": {
            "name": "Animal",
            "_embedded": { "metadata": { "id": "2" } }
          }
        }
      },
      {
        "name": "Jellyfish",
        "_embedded": {
          "metadata": { "id": "332" },
          "category": {
            "name": "Animal",
            "_embedded": { "metadata": { "id": "2" } }
          }
        }
      },
      {
        "name": "Squid",
        "_embedded": {
          "metadata": { "id": "333" },
          "category": {
            "name": "Animal",
            "_embedded": { "metadata": { "id": "2" } }
          }
        }
      },
      {
        "name": "Lobster",
        "_embedded": {
          "metadata": { "id": "334" },
          "category": {
            "name": "Animal",
            "_embedded": { "metadata": { "id": "2" } }
          }
        }
      },
      {
        "name": "Pelican",
        "_embedded": {
          "metadata": { "id": "335" },
          "category": {
            "name": "Animal",
            "_embedded": { "metadata": { "id": "2" } }
          }
        }
      },
      {
        "name": "Clams",
        "_embedded": {
          "metadata": { "id": "336" },
          "category": {
            "name": "Animal",
            "_embedded": { "metadata": { "id": "2" } }
          }
        }
      },
      {
        "name": "Seagull",
        "_embedded": {
          "metadata": { "id": "337" },
          "category": {
            "name": "Animal",
            "_embedded": { "metadata": { "id": "2" } }
          }
        }
      },
      {
        "name": "Dolphin",
        "_embedded": {
          "metadata": { "id": "338" },
          "category": {
            "name": "Animal",
            "_embedded": { "metadata": { "id": "2" } }
          }
        }
      },
      {
        "name": "Shells",
        "_embedded": {
          "metadata": { "id": "339" },
          "category": {
            "name": "Animal",
            "_embedded": { "metadata": { "id": "2" } }
          }
        }
      },
      {
        "name": "Sea urchin",
        "_embedded": {
          "metadata": { "id": "340" },
          "category": {
            "name": "Animal",
            "_embedded": { "metadata": { "id": "2" } }
          }
        }
      },
      {
        "name": "Cormorant",
        "_embedded": {
          "metadata": { "id": "341" },
          "category": {
            "name": "Animal",
            "_embedded": { "metadata": { "id": "2" } }
          }
        }
      },
      {
        "name": "Otter",
        "_embedded": {
          "metadata": { "id": "342" },
          "category": {
            "name": "Animal",
            "_embedded": { "metadata": { "id": "2" } }
          }
        }
      },
      {
        "name": "Pelican",
        "_embedded": {
          "metadata": { "id": "343" },
          "category": {
            "name": "Animal",
            "_embedded": { "metadata": { "id": "2" } }
          }
        }
      },
      {
        "name": "Sea anemone",
        "_embedded": {
          "metadata": { "id": "344" },
          "category": {
            "name": "Animal",
            "_embedded": { "metadata": { "id": "2" } }
          }
        }
      },
      {
        "name": "Sea turtle",
        "_embedded": {
          "metadata": { "id": "345" },
          "category": {
            "name": "Animal",
            "_embedded": { "metadata": { "id": "2" } }
          }
        }
      },
      {
        "name": "Sea lion",
        "_embedded": {
          "metadata": { "id": "346" },
          "category": {
            "name": "Animal",
            "_embedded": { "metadata": { "id": "2" } }
          }
        }
      },
      {
        "name": "Coral",
        "_embedded": {
          "metadata": { "id": "347" },
          "category": {
            "name": "Animal",
            "_embedded": { "metadata": { "id": "2" } }
          }
        }
      },
      {
        "name": "Moth",
        "_embedded": {
          "metadata": { "id": "348" },
          "category": {
            "name": "Animal",
            "_embedded": { "metadata": { "id": "2" } }
          }
        }
      },
      {
        "name": "Bee",
        "_embedded": {
          "metadata": { "id": "349" },
          "category": {
            "name": "Animal",
            "_embedded": { "metadata": { "id": "2" } }
          }
        }
      },
      {
        "name": "Butterfly",
        "_embedded": {
          "metadata": { "id": "350" },
          "category": {
            "name": "Animal",
            "_embedded": { "metadata": { "id": "2" } }
          }
        }
      },
      {
        "name": "Spider",
        "_embedded": {
          "metadata": { "id": "351" },
          "category": {
            "name": "Animal",
            "_embedded": { "metadata": { "id": "2" } }
          }
        }
      },
      {
        "name": "Ladybird",
        "_embedded": {
          "metadata": { "id": "352" },
          "category": {
            "name": "Animal",
            "_embedded": { "metadata": { "id": "2" } }
          }
        }
      },
      {
        "name": "Ant",
        "_embedded": {
          "metadata": { "id": "353" },
          "category": {
            "name": "Animal",
            "_embedded": { "metadata": { "id": "2" } }
          }
        }
      },
      {
        "name": "Dragonfly",
        "_embedded": {
          "metadata": { "id": "354" },
          "category": {
            "name": "Animal",
            "_embedded": { "metadata": { "id": "2" } }
          }
        }
      },
      {
        "name": "Fly",
        "_embedded": {
          "metadata": { "id": "355" },
          "category": {
            "name": "Animal",
            "_embedded": { "metadata": { "id": "2" } }
          }
        }
      },
      {
        "name": "Mosquito",
        "_embedded": {
          "metadata": { "id": "356" },
          "category": {
            "name": "Animal",
            "_embedded": { "metadata": { "id": "2" } }
          }
        }
      },
      {
        "name": "Grasshopper",
        "_embedded": {
          "metadata": { "id": "357" },
          "category": {
            "name": "Animal",
            "_embedded": { "metadata": { "id": "2" } }
          }
        }
      },
      {
        "name": "Beetle",
        "_embedded": {
          "metadata": { "id": "358" },
          "category": {
            "name": "Animal",
            "_embedded": { "metadata": { "id": "2" } }
          }
        }
      },
      {
        "name": "Cockroach",
        "_embedded": {
          "metadata": { "id": "359" },
          "category": {
            "name": "Animal",
            "_embedded": { "metadata": { "id": "2" } }
          }
        }
      },
      {
        "name": "Centipede",
        "_embedded": {
          "metadata": { "id": "360" },
          "category": {
            "name": "Animal",
            "_embedded": { "metadata": { "id": "2" } }
          }
        }
      },
      {
        "name": "Worm",
        "_embedded": {
          "metadata": { "id": "361" },
          "category": {
            "name": "Animal",
            "_embedded": { "metadata": { "id": "2" } }
          }
        }
      },
      {
        "name": "Louse",
        "_embedded": {
          "metadata": { "id": "362" },
          "category": {
            "name": "Animal",
            "_embedded": { "metadata": { "id": "2" } }
          }
        }
      }
    ]
  }
}
